catanatron/__init__.py
catanatron/game.py
catanatron/json.py
catanatron/state.py
catanatron/state_functions.py
catanatron/models/__init__.py
catanatron/models/actions.py
catanatron/models/board.py
catanatron/models/coordinate_system.py
catanatron/models/decks.py
catanatron/models/enums.py
catanatron/models/map.py
catanatron/models/player.py
catanatron/players/__init__.py
catanatron/players/search.py
catanatron/players/weighted_random.py
catanatron-3.2.1.dist-info/METADATA
catanatron-3.2.1.dist-info/WHEEL
catanatron-3.2.1.dist-info/top_level.txt
catanatron-3.2.1.dist-info/RECORD
