Metadata-Version: 2.1
Name: catanatron
Version: 3.2.1
Summary: Fast Settlers of Catan Python Implementation
Home-page: https://github.com/bcollazo/catanatron
Author: Bryan Collazo
Author-email: bcollazo2010@gmail.com
License: UNKNOWN
Platform: UNKNOWN
Classifier: Programming Language :: Python :: 3
Classifier: License :: OSI Approved :: MIT License
Classifier: Operating System :: OS Independent
Requires-Python: >=3.6
Requires-Dist: networkx
